freeutils/__init__.py
freeutils/mydecimal.py
freeutils/mystring.py
freeutils-1.0.0.dist-info/METADATA
freeutils-1.0.0.dist-info/WHEEL
freeutils-1.0.0.dist-info/RECORD
